HW_DSD_CPU_402106112/src/memory.v
module memory (
    input clk, 
    input write_enable, read_enable,
    input [15:0] address,
    input [15:0] write_data,
    output reg [15:0] read_data  
);

    localparam MEM_DEPTH = 1 << 16; // This gives 2^16

    reg [15:0] mem [0:MEM_DEPTH-1]; // 2^16 words, each 16-bit

    always @(posedge clk) begin
        if (write_enable) 
            mem[address] <= write_data;
        else if (read_enable)
            read_data <= mem[address]; 
    end
endmodule

exercise_3/verilog_codes/memory_tb.v
module memory_tb ();

    localparam CLK_PERIOD = 2;

    reg clk;
    reg write_enable, read_enable;
    reg [15:0] address;
    reg signed [15:0] write_data;
    wire signed [15:0] read_data;

    memory mem_inst (clk, write_enable, read_enable, address, write_data, read_data);
    
    always #(CLK_PERIOD/2) clk = ~clk;

    // Two tasks : For reading and writing data
    task write_mem(input [15:0] addr, input [15:0] data);
    begin
        write_enable = 1;
        address = addr;
        write_data = data;
        #CLK_PERIOD; // We wait one clock cycle to writing completion
    end
    endtask

    task read_mem(input [15:0] addr);
    begin
        read_enable = 1;
        address = addr;
        #CLK_PERIOD; // We wait one clock cycle to reading completion
        $display("Read mem[%0d]: %0d (exp: %0d)", addr, read_data, $signed(mem_inst.mem[addr]));
    end
    endtask


    initial begin
        $dumpfile("memory.vcd");
        $dumpvars(0, memory_tb);

        clk = 0;
        write_enable = 0; read_enable = 0; address = 0; write_data = 0;
        
        #CLK_PERIOD;
        // Write values
        write_mem(16'd10, -16'd1234);
        write_mem(16'd110, 16'd5678);
        write_mem(16'd1200, 16'd9999);
        
        write_enable = 0;

        // Read values
        read_mem(16'd10);
        read_mem(16'd110);
        read_mem(16'd1200);
        read_mem(16'd1000);
        
        read_enable = 0;

        $finish;
    end
endmodule

HW_DSD_CPU_402106112/src/memory.vcd
$date
	Thu Jul 10 19:25:25 2025
$end
$version
	Icarus Verilog
$end
$timescale
	1s
$end
$scope module memory_tb $end
$var wire 16 ! read_data [15:0] $end
$var parameter 32 " CLK_PERIOD $end
$var reg 16 # address [15:0] $end
$var reg 1 $ clk $end
$var reg 1 % read_enable $end
$var reg 16 & write_data [15:0] $end
$var reg 1 ' write_enable $end
$scope module mem_inst $end
$var wire 16 ( address [15:0] $end
$var wire 1 $ clk $end
$var wire 1 % read_enable $end
$var wire 16 ) write_data [15:0] $end
$var wire 1 ' write_enable $end
$var parameter 48 * MEM_DEPTH $end
$var reg 16 + read_data [15:0] $end
$upscope $end
$scope task read_mem $end
$var reg 16 , addr [15:0] $end
$upscope $end
$scope task write_mem $end
$var reg 16 - addr [15:0] $end
$var reg 16 . data [15:0] $end
$upscope $end
$upscope $end
$enddefinitions $end
$comment Show the parameter values. $end
$dumpall
b10000000000000000 *
b10 "
$end
#0
$dumpvars
bx .
bx -
bx ,
bx +
b0 )
b0 (
0'
b0 &
0%
0$
b0 #
bx !
$end
#1
1$
#2
0$
b1111101100101110 &
b1111101100101110 )
b1010 #
b1010 (
1'
b1111101100101110 .
b1010 -
#3
1$
#4
0$
b1011000101110 &
b1011000101110 )
b1101110 #
b1101110 (
b1011000101110 .
b1101110 -
#5
1$
#6
0$
b10011100001111 &
b10011100001111 )
b10010110000 #
b10010110000 (
b10011100001111 .
b10010110000 -
#7
1$
#8
0$
b1010 #
b1010 (
1%
b1010 ,
0'
#9
b1111101100101110 !
b1111101100101110 +
1$
#10
0$
b1101110 #
b1101110 (
b1101110 ,
#11
b1011000101110 !
b1011000101110 +
1$
#12
0$
b10010110000 #
b10010110000 (
b10010110000 ,
#13
b10011100001111 !
b10011100001111 +
1$
#14
0$
b1111101000 #
b1111101000 (
b1111101000 ,
#15
bx !
bx +
1$
#16
0$
0%
