HW_DSD_CPU_402106112/src/register_file.v
module register_file (
    input clk, reset, 
    input write_enable, 
    input [1:0] write_reg_num, read_reg_1_num, read_reg_2_num,
    input [15:0] write_data,
    output reg [15:0] read_data_1, read_data_2
);

    reg [15:0] registers[3:0];

    // Write is done on rising edge of clock 
    integer i;
    always @(posedge clk) begin
        if (reset) begin
            for (i = 0; i < 4; i = i + 1)
                registers[i] <= 16'd0;
        end else if (write_enable) begin
            registers[write_reg_num] <= write_data;     
        end
    end

    // Read is done on falling edge of clock
    always @(negedge clk) begin
        read_data_1 <= registers[read_reg_1_num];
        read_data_2 <= registers[read_reg_2_num];
    end

endmodule

HW_DSD_CPU_402106112/src/register_file_tb.v
module register_file_tb ();
    localparam CLK_PERIOD = 2;

    reg clk, reset, write_enable;
    reg [1:0] write_reg_num, read_reg_1_num, read_reg_2_num;
    reg signed [15:0] write_data;
    wire signed [15:0] read_data_1, read_data_2;

    register_file rf (clk, reset, write_enable, write_reg_num,
        read_reg_1_num, read_reg_2_num, write_data, read_data_1, read_data_2);

    always #(CLK_PERIOD/2) clk = ~clk;

    initial begin
        $dumpfile("register_file.vcd");
        $dumpvars(0, register_file_tb);

        clk = 0;
        reset = 1;
        write_enable = 0;
        write_reg_num = 0;
        write_data = -1404;

        @(posedge clk); // writing on posedge
        reset = 0;
        write_enable = 1;
        #CLK_PERIOD;

        // Write to registers x0 to x3
        repeat (3) begin // This is nice syntax. It is equal to for (i = 0; i < 4; i = i + 1)
            write_reg_num = write_reg_num + 1;
            write_data = write_data + 1000;
            #CLK_PERIOD;
        end

        write_enable = 0;

        read_reg_1_num = 1;
        read_reg_2_num = 2;
        #CLK_PERIOD;
        $display("Read x1 = %d (exp -404), x2 = %d (exp 596)", read_data_1, read_data_2);

        read_reg_1_num = 3;
        read_reg_2_num = 0;
        #CLK_PERIOD;
        $display("Read x3 = %d (exp 1596), x0 = %d (exp -1404)", read_data_1, read_data_2);

        @(posedge clk); // Writing on posedge (we can also use #CLK_PERIOD;)
        write_enable = 1;
        write_reg_num = 1;
        write_data = 4321;

        #CLK_PERIOD
        write_enable = 0;
        read_reg_2_num = 1;
        #CLK_PERIOD;
        $display("Read x3 = %d (exp 1596), x1 = %d (exp 4321)", read_data_1, read_data_2);

        @(posedge clk); // In this part I can also use #(CLK_PERIOD/2) to change registers on posedge (or wait 2*CLK_PERIOD after reset = 1)
        reset = 1;
        #CLK_PERIOD;
        $display("Read x3 = %d (exp 0), x1 = %d (exp 0)", read_data_1, read_data_2);
        
        $finish;
    end

endmodule

HW_DSD_CPU_402106112/src/register_file.vcd
$date
	Wed Jul 09 18:15:02 2025
$end
$version
	Icarus Verilog
$end
$timescale
	1s
$end
$scope module register_file_tb $end
$var wire 16 ! read_data_2 [15:0] $end
$var wire 16 " read_data_1 [15:0] $end
$var parameter 32 # CLK_PERIOD $end
$var reg 1 $ clk $end
$var reg 2 % read_reg_1_num [1:0] $end
$var reg 2 & read_reg_2_num [1:0] $end
$var reg 1 ' reset $end
$var reg 16 ( write_data [15:0] $end
$var reg 1 ) write_enable $end
$var reg 2 * write_reg_num [1:0] $end
$scope module rf $end
$var wire 1 $ clk $end
$var wire 2 + read_reg_1_num [1:0] $end
$var wire 2 , read_reg_2_num [1:0] $end
$var wire 1 ' reset $end
$var wire 16 - write_data [15:0] $end
$var wire 1 ) write_enable $end
$var wire 2 . write_reg_num [1:0] $end
$var reg 16 / read_data_1 [15:0] $end
$var reg 16 0 read_data_2 [15:0] $end
$var integer 32 1 i [31:0] $end
$upscope $end
$upscope $end
$enddefinitions $end
$comment Show the parameter values. $end
$dumpall
b10 #
$end
#0
$dumpvars
bx 1
bx 0
bx /
b0 .
b1111101010000100 -
bx ,
bx +
b0 *
0)
b1111101010000100 (
1'
bx &
bx %
0$
bx "
bx !
$end
#1
1)
0'
1$
#2
0$
#3
1$
b1111111001101100 (
b1111111001101100 -
b1 *
b1 .
#4
0$
#5
1$
b1001010100 (
b1001010100 -
b10 *
b10 .
#6
0$
#7
1$
b11000111100 (
b11000111100 -
b11 *
b11 .
#8
0$
#9
1$
b10 &
b10 ,
b1 %
b1 +
0)
#10
b1001010100 !
b1001010100 0
b1111111001101100 "
b1111111001101100 /
0$
#11
1$
b0 &
b0 ,
b11 %
b11 +
#12
b1111101010000100 !
b1111101010000100 0
b11000111100 "
b11000111100 /
0$
#13
b1000011100001 (
b1000011100001 -
b1 *
b1 .
1)
1$
#14
0$
#15
1$
b1 &
b1 ,
0)
#16
b1000011100001 !
b1000011100001 0
0$
#17
b100 1
1'
1$
#18
b0 !
b0 0
b0 "
b0 /
0$
#19
b100 1
1$
